easysettings/__init__.py
easysettings/app.py
easysettings/legacy.py
easysettings/tests/__init__.py
easysettings/tests/examples.py
easysettings/tests/test_app.py
easysettings/tests/test_legacy.py
django_easysettings-2.0.1.dist-info/METADATA
django_easysettings-2.0.1.dist-info/WHEEL
django_easysettings-2.0.1.dist-info/top_level.txt
django_easysettings-2.0.1.dist-info/RECORD
