Metadata-Version: 2.1
Name: django-easysettings
Version: 2.0.1
Summary: Easy app-specific settings for Django
Home-page: http://github.com/SmileyChris/django-easysettings
Author: Chris Beaven
Author-email: smileychris@gmail.com
License: BSD
Platform: UNKNOWN
Classifier: Development Status :: 4 - Beta
Classifier: Environment :: Web Environment
Classifier: Framework :: Django
Classifier: Intended Audience :: Developers
Classifier: License :: OSI Approved :: BSD License
Classifier: Operating System :: OS Independent
Classifier: Programming Language :: Python
Classifier: Programming Language :: Python :: 2.7
Classifier: Programming Language :: Python :: 3
Classifier: Programming Language :: Python :: 3.6
Classifier: Programming Language :: Python :: 3.7
Classifier: Topic :: Software Development :: Libraries :: Application Frameworks
Classifier: Topic :: Software Development :: Libraries :: Python Modules
Provides-Extra: dev
Requires-Dist: tox ; extra == 'dev'
Requires-Dist: django ; extra == 'dev'
Requires-Dist: pytest-mock ; extra == 'dev'
Provides-Extra: maintainer
Requires-Dist: zest.releaser[recommended] ; extra == 'maintainer'
Provides-Extra: test
Requires-Dist: pytest-mock ; extra == 'test'
Requires-Dist: pytest-cov ; extra == 'test'
